pilabs/pi_ragbox/__about__.py
pilabs/pi_ragbox/__init__.py
pilabs/pi_ragbox/api.py
pilabs/pi_ragbox/auth.py
pilabs/pi_ragbox/config.py
pilabs/pi_ragbox/main.py
pilabs/pi_ragbox/watcher.py
pilabs/data_model/__init__.pyi
pilabs/data_model/document_model.pyi
pilabs/data_model/feature_model.pyi
pilabs/data_model/index_document_model.pyi
pilabs/data_model/param_model.pyi
pilabs/data_model/piragbox_model.pyi
pilabs/data_model/query_model.pyi
pilabs/data_model/request_context_model.pyi
pilabs/data_model/retrieval_model.pyi
pilabs/indexer/__init__.py
pilabs/indexer/piragbox_indexer.py
pilabs/indexing_client/__init__.py
pilabs/indexing_client/indexing_client.py
pilabs/indexing_model/__init__.py
pilabs/indexing_model/index_document_model.py
pilabs/indexing_model/test_index_document_model.py
pilabs/search_service/__init__.pyi
pilabs/search_service/main.pyi
pilabs/search_service/modal_main.pyi
pilabs/search_service/py.typed
pilabs/search_service/builtin_flows/pi_flows/__init__.py
pilabs/search_service/builtin_flows/pi_flows/requirements.txt
pilabs/search_service/builtin_flows/pi_flows/search_simple.py
pi_ragbox-0.0.14.dist-info/METADATA
pi_ragbox-0.0.14.dist-info/WHEEL
pi_ragbox-0.0.14.dist-info/entry_points.txt
pi_ragbox-0.0.14.dist-info/RECORD
