Metadata-Version: 2.4
Name: pi-ragbox
Version: 0.0.14
Summary: Pi-RagBox CLI tool
Author-email: Zach Clifford <zach@withpi.ai>
License-Expression: LicenseRef-PiLabs-Proprietary
Classifier: Development Status :: 3 - Alpha
Classifier: Intended Audience :: Developers
Classifier: Programming Language :: Python :: 3
Classifier: Programming Language :: Python :: 3.13
Requires-Python: <3.14,>=3.13
Requires-Dist: boto3>=1.34.0
Requires-Dist: click>=8.0.0
Requires-Dist: datasets>=3.6.0
Requires-Dist: httpx>=0.27.0
Requires-Dist: opensearch-py>=2.4.0
Requires-Dist: platformdirs>=4.0.0
Requires-Dist: pydantic>=2.12.3
Requires-Dist: python-dotenv>=1.1.1
Requires-Dist: requests-aws4auth>=1.2.3
Requires-Dist: rich>=13.0.0
Requires-Dist: typer>=0.20.0
Requires-Dist: watchdog>=4.0.0
Requires-Dist: websockets>=12.0
